LICENSE
MANIFEST.in
README.rst
setup.cfg
setup.py
tests/__init__.py
tests/test_exception.py
tests/test_related.py
tests/test_utils.py
tests/test_widgets.py
tests/testapi.py
tw2/__init__.py
tw2.sqla.egg-info/PKG-INFO
tw2.sqla.egg-info/SOURCES.txt
tw2.sqla.egg-info/dependency_links.txt
tw2.sqla.egg-info/entry_points.txt
tw2.sqla.egg-info/namespace_packages.txt
tw2.sqla.egg-info/not-zip-safe
tw2.sqla.egg-info/requires.txt
tw2.sqla.egg-info/top_level.txt
tw2/sqla/__init__.py
tw2/sqla/compat.py
tw2/sqla/factory.py
tw2/sqla/utils.py
tw2/sqla/widgets.py
tw2/sqla/templates/__init__.py
tw2/sqla/templates/__init__.pyc
tw2/sqla/templates/dblistpage.html
tw2/sqla/templates/dblistpage.mak