Metadata-Version: 1.1
Name: tw2.sqla
Version: 2.1.0
Summary: SQLAlchemy database layer for ToscaWidgets 2, a web widget toolkit.
Home-page: http://github.com/toscawidgets/tw2.sqla
Author: Paul Johnston
Author-email: paj@pajhome.org.uk
License: MIT
Download-URL: https://pypi.python.org/pypi/tw2.sqla/
Keywords: toscawidgets.widgets
Platform: UNKNOWN
Classifier: Development Status :: 3 - Alpha
Classifier: Environment :: Web Environment
Classifier: Environment :: Web Environment :: ToscaWidgets
Classifier: Topic :: Software Development :: Libraries :: Python Modules
Classifier: Topic :: Software Development :: Widget Sets
Classifier: Intended Audience :: Developers
Classifier: Operating System :: OS Independent
Classifier: Programming Language :: Python
Classifier: Programming Language :: Python :: 2
Classifier: Programming Language :: Python :: 2.6
Classifier: Programming Language :: Python :: 2.7
